cyutils/__init__.py
cyutils/exception_handler.py
cyutils/io/__init__.py
cyutils/io/colored_text.py
cyutils/io/custom_error.py
cyutils/io/message_boxes.py
cyutils/tools/__init__.py
cyutils/tools/cipher.py
cyutils/tools/lists.py
cyutils/tools/math.py
cyutils-0.0.10.dist-info/METADATA
cyutils-0.0.10.dist-info/WHEEL
cyutils-0.0.10.dist-info/top_level.txt
cyutils-0.0.10.dist-info/RECORD
