Metadata-Version: 2.1
Name: cyutils
Version: 0.0.10
Summary: Utilities by cy4
Home-page: UNKNOWN
Author: Cy4
License: MIT
Keywords: Cy4,Cy,CyUtils
Platform: UNKNOWN
Requires-Python: >=3.6
Requires-Dist: numpy
